common/__init__.py
common/decoration.py
common/descriptors.py
common/errors.py
common/metaclasses.py
common/utils.py
common/variables.py
server/__init__.py
server/add_user.py
server/config_window.py
server/core.py
server/database.py
server/main_window.py
server/remove_user.py
server/stat_window.py
server_part-0.0.1.dist-info/METADATA
server_part-0.0.1.dist-info/WHEEL
server_part-0.0.1.dist-info/top_level.txt
server_part-0.0.1.dist-info/RECORD
