Metadata-Version: 2.1
Name: server-part
Version: 0.0.1
Summary: server_part_pyqt
Author: Vyacheslav
Author-email: rgka17@yandex.ru
License: UNKNOWN
Platform: UNKNOWN
Requires-Dist: PyQt5
Requires-Dist: sqlalchemy
Requires-Dist: pycrypto
Requires-Dist: pycryptodomex
